dtranslate/README.MD
dtranslate/__init__.py
dtranslate/requirements.txt
dtranslate/thirdparty.json
dtranslate-0.10.dist-info/LICENSE.rst
dtranslate-0.10.dist-info/METADATA
dtranslate-0.10.dist-info/WHEEL
dtranslate-0.10.dist-info/top_level.txt
dtranslate-0.10.dist-info/RECORD
