Metadata-Version: 2.1
Name: dtranslate
Version: 0.10
Summary: automates text translation using Deepl Translate
Home-page: https://github.com/hansalemaos/dtranslate
Author: Johannes Fischer
Author-email: aulasparticularesdealemaosp@gmail.com
License: MIT
Keywords: Deepl,translate
Classifier: Development Status :: 4 - Beta
Classifier: Programming Language :: Python :: 3 :: Only
Classifier: Programming Language :: Python :: 3.10
Classifier: Topic :: Software Development :: Libraries :: Python Modules
Classifier: Topic :: Utilities
License-File: LICENSE.rst
Requires-Dist: kthread-sleep
Requires-Dist: retryloop
Requires-Dist: selenium
Requires-Dist: translate4colors
